README.rst
latexmake.py
setup.py
latexmk.py.egg-info/PKG-INFO
latexmk.py.egg-info/SOURCES.txt
latexmk.py.egg-info/dependency_links.txt
latexmk.py.egg-info/entry_points.txt
latexmk.py.egg-info/top_level.txt