Metadata-Version: 1.0
Name: latexmk.py
Version: 0.4
Summary: Latexmk.py completely automates the process of generating a LaTeX document.
Home-page: http://github.com/schlamar/latexmk.py
Author: Marc Schlaich
Author-email: marc.schlaich@googlemail.com
License: MIT
Platform: any
Classifier: Development Status :: 4 - Beta
Classifier: Intended Audience :: End Users/Desktop
Classifier: License :: OSI Approved :: MIT License
Classifier: Operating System :: OS Independent
Classifier: Programming Language :: Python
Classifier: Programming Language :: Python :: 2
Classifier: Programming Language :: Python :: 3
Classifier: Topic :: Printing
Classifier: Topic :: Text Processing :: Markup :: LaTeX
